flexiblecc/__init__.py
flexiblecc/BSpline/__init__.py
flexiblecc/BSpline/basis_test.py
flexiblecc/BSpline/central_model.py
flexiblecc/BSpline/generate_points.py
flexiblecc/BSpline/knot_generators.py
flexiblecc/BundleAdjustment/__init__.py
flexiblecc/BundleAdjustment/bundle_adjustment.py
flexiblecc/BundleAdjustment/check_normal_res.py
flexiblecc/BundleAdjustment/chessboard_bundle_adjustment.py
flexiblecc/BundleAdjustment/initialization.py
flexiblecc/BundleAdjustment/load_bundle_adjustment_results.py
flexiblecc/BundleAdjustment/testcheckboard.py
flexiblecc/BundleAdjustment/teststuff.py
flexiblecc/BundleAdjustment/to_be_removed_calibrate.py
flexiblecc/BundleAdjustment/to_be_removed_central_model.py
flexiblecc/BundleAdjustment/to_be_removed_knot_generators.py
flexiblecc/CentralModel/__init__.py
flexiblecc/CentralModel/BSpline/__init__.py
flexiblecc/CentralModel/BSpline/basis_test.py
flexiblecc/CentralModel/BSpline/central_model.py
flexiblecc/CentralModel/BSpline/generate_points.py
flexiblecc/CentralModel/BSpline/knot_generators.py
flexiblecc/CentralModel/BundleAdjustment/__init__.py
flexiblecc/CentralModel/BundleAdjustment/bundle_adjustment.py
flexiblecc/CentralModel/BundleAdjustment/initialization.py
flexiblecc/Metrics/__init__.py
flexiblecc/Metrics/centralmodel.py
flexiblecc/Metrics/distorsion.py
flexiblecc/Metrics/rtvecs_illustration.py
flexiblecc/Metrics/stats.py
flexiblecc/Metrics/voronoi.py
flexiblecc/OldSchoolCC/__init__.py
flexiblecc/OldSchoolCC/calibrate.py
flexiblecc/Parametric/__init__.py
flexiblecc/Parametric/calibrate.py
flexiblecc-1.0.0.dist-info/LICENSE
flexiblecc-1.0.0.dist-info/METADATA
flexiblecc-1.0.0.dist-info/WHEEL
flexiblecc-1.0.0.dist-info/top_level.txt
flexiblecc-1.0.0.dist-info/RECORD
