Metadata-Version: 2.1
Name: flexiblecc
Version: 1.0.0
Summary: Flexible Camera Calibration
Home-page: https://github.com/SimonLBSoerensen/Flexible-Camera-Calibration
Author: Simon L. B. Sørensen and contributors
Author-email: simonlyckbjaert@hotmail.com
License: MIT
Keywords: camera calibration
Platform: UNKNOWN
Classifier: Programming Language :: Python :: 3
Classifier: License :: OSI Approved :: MIT License
Classifier: Operating System :: OS Independent
Requires-Python: >=3.6
Requires-Dist: numpy
Requires-Dist: opencv-contrib-python (>=3.1)
Requires-Dist: tqdm
Requires-Dist: matplotlib
Requires-Dist: scipy
Requires-Dist: Pillow
Requires-Dist: seaborn
Requires-Dist: pandas
